moskali/__init__.py
moskali/losses.txt
moskali/main.py
moskali-5.dist-info/LICENCE
moskali-5.dist-info/METADATA
moskali-5.dist-info/WHEEL
moskali-5.dist-info/entry_points.txt
moskali-5.dist-info/top_level.txt
moskali-5.dist-info/RECORD
