Metadata-Version: 2.1
Name: moskali
Version: 5
Summary: Very useful code
Home-page: http://github.com/dummy_user/useful
Author: Oleh Andrus
Author-email: andrus@test.gmail.com
License: MIT
Platform: UNKNOWN
Classifier: Programming Language :: Python :: 3
Requires-Dist: faker
